LICENSE.md
README.md
setup.py
pipall/__init__.py
pipall/installer.py
pipall.egg-info/PKG-INFO
pipall.egg-info/SOURCES.txt
pipall.egg-info/dependency_links.txt
pipall.egg-info/entry_points.txt
pipall.egg-info/top_level.txt