Metadata-Version: 2.1
Name: pipall
Version: 0.0.6
Summary: PipAll is a Python library management tool that simplifies the installation, uninstallation, and listing of libraries for different Python versions.
Author: Sree Harsha
Author-email: sreeharsha120203@gmail.com
Keywords: pipall,pythonversions
License-File: LICENSE.md
